.gitignore
LICENSE.txt
debian_show_depends.sh
generate_depends_list.sh
setup.py
motmot/__init__.py
motmot.utils.egg-info/.gitignore
motmot.utils.egg-info/PKG-INFO
motmot.utils.egg-info/SOURCES.txt
motmot.utils.egg-info/dependency_links.txt
motmot.utils.egg-info/entry_points.txt
motmot.utils.egg-info/namespace_packages.txt
motmot.utils.egg-info/stdeb.cfg
motmot.utils.egg-info/top_level.txt
motmot/utils/__init__.py
motmot/utils/check_new_namespace.py
motmot/utils/config.py
motmot/utils/utils.py