Metadata-Version: 1.0
Name: motmot.utils
Version: 20090612
Summary: miscellaneous utilities for the motmot camera packages
Home-page: http://code.astraw.com/projects/motmot
Author: Andrew Straw
Author-email: strawman@astraw.com
License: BSD
Platform: UNKNOWN
